{
	"configurations" : 
	[
		{
			"directories" : 
			[
				{
					"build" : ".",
					"hasInstallRule" : true,
					"jsonFile" : "directory-.-b829f1b1c7c7633cd7ed.json",
					"minimumCMakeVersion" : 
					{
						"string" : "3.12"
					},
					"projectIndex" : 0,
					"source" : ".",
					"targetIndexes" : 
					[
						0,
						1
					]
				}
			],
			"name" : "",
			"projects" : 
			[
				{
					"directoryIndexes" : 
					[
						0
					],
					"name" : "legacy_moveit",
					"targetIndexes" : 
					[
						0,
						1
					]
				}
			],
			"targets" : 
			[
				{
					"directoryIndex" : 0,
					"id" : "legacy_moveit_uninstall::@6890427a1f51a3e7e1df",
					"jsonFile" : "target-legacy_moveit_uninstall-cb2e70a195ae23745de8.json",
					"name" : "legacy_moveit_uninstall",
					"projectIndex" : 0
				},
				{
					"directoryIndex" : 0,
					"id" : "uninstall::@6890427a1f51a3e7e1df",
					"jsonFile" : "target-uninstall-94409e86a4ba511f1eab.json",
					"name" : "uninstall",
					"projectIndex" : 0
				}
			]
		}
	],
	"kind" : "codemodel",
	"paths" : 
	{
		"build" : "/home/roar/new_arm/old_ROAR_arm/build/legacy_moveit",
		"source" : "/home/roar/new_arm/old_ROAR_arm/src/legacy_moveit"
	},
	"version" : 
	{
		"major" : 2,
		"minor" : 3
	}
}
